README.md
setup.py
lsjtools/__init__.py
lsjtools.egg-info/PKG-INFO
lsjtools.egg-info/SOURCES.txt
lsjtools.egg-info/dependency_links.txt
lsjtools.egg-info/top_level.txt
lsjtools/lh/__init__.py
lsjtools/lh/_core.py
lsjtools/lh/biying.py
lsjtools/ml/__init__.py
lsjtools/ml/_core.py
lsjtools/util/__init__.py
lsjtools/util/_core.py