Metadata-Version: 2.1
Name: lsjtools
Version: 1.0.5
Summary: Python环境下的工具库
Home-page: https://gitee.com/linxm/lsjtools.git
Author: Linxm
Author-email: 547304723@qq.com
License: Apache 2.0
Keywords: lsjtools
Classifier: Development Status :: 3 - Alpha
Classifier: Intended Audience :: Developers
Classifier: Programming Language :: Python :: 3.8
Classifier: License :: OSI Approved :: MIT License
Classifier: Topic :: Utilities
Classifier: Operating System :: OS Independent
Requires-Python: >=3.6
